{
    "id": 114959709,
    "name": "GEEF",
    "author": "Kyrintu",
    "creators": ["Kyrintu"],
    "verifier": "Kyrintu",
    "verification": "https://www.youtube.com/watch?v=qq8Nnu-SqZI",
    "percentToQualify": "100",
    "password": "Free To Copy",
    "records": [
        {
            "user": "mastersensi",
            "link": "https://drive.google.com/file/d/1XXLakuTK4ruwgxt7Yr9v5aJ7tcyHDdeF/view",
            "percent": 100,
            "hz": 60
        },
        {
            "user": "empty",
            "link": "also empty",
            "percent": 100,
            "hz": 60
        }
    ]
}
